JetKVM/JetKVM.py
JetKVM/__init__.py
JetKVM-0.0.1.dist-info/METADATA
JetKVM-0.0.1.dist-info/WHEEL
JetKVM-0.0.1.dist-info/top_level.txt
JetKVM-0.0.1.dist-info/RECORD
